imagery24/__init__.py
imagery24/extract.py
imagery24/georeference.py
imagery24/graph.py
imagery24/kml_to_geotiff.py
imagery24/main.py
imagery24/split_polygons.py
imagery24/tags.py
imagery24/tiff.py
imagery24/tiles.py
imagery24/utils.py
imagery24-0.11.0.dist-info/METADATA
imagery24-0.11.0.dist-info/WHEEL
imagery24-0.11.0.dist-info/top_level.txt
imagery24-0.11.0.dist-info/zip-safe
imagery24-0.11.0.dist-info/RECORD
