Metadata-Version: 2.4
Name: imagery24
Version: 0.11.0
Summary: A short description of your package
Author-email: your.email@example.com
License: MIT
Classifier: Programming Language :: Python :: 3
Classifier: License :: OSI Approved :: MIT License
Classifier: Operating System :: OS Independent
Requires-Python: >=3.6
Requires-Dist: rasterio==1.4.3
Requires-Dist: pillow==11.1.0
Requires-Dist: imagecodecs==2024.12.30
Requires-Dist: geopandas==1.0.1
Requires-Dist: matplotlib==3.10.0
Requires-Dist: pykml==0.2.0
Requires-Dist: centerline==1.1.1
Requires-Dist: networkx==3.4.2
Requires-Dist: shapely==2.1.1
Dynamic: author-email
Dynamic: classifier
Dynamic: description-content-type
Dynamic: license
Dynamic: requires-dist
Dynamic: requires-python
Dynamic: summary
